Metadata-Version: 1.1
Name: django-simple-authentication
Version: 0.1.2
Summary: Email identification authentication app for Django.
Home-page: https://github.com/teapow/django-simple-authentication
Author: Thomas Power
Author-email: thomaspwr@gmail.com
License: MIT
Platform: UNKNOWN
Classifier: Framework :: Django
Classifier: Framework :: Django :: 2.0
Classifier: Framework :: Django :: 2.1
Classifier: Programming Language :: Python
Classifier: Programming Language :: Python :: 3
Classifier: Topic :: Utilities
